inputter/__init__.py
inputter-0.0.1.dist-info/LICENCE
inputter-0.0.1.dist-info/METADATA
inputter-0.0.1.dist-info/WHEEL
inputter-0.0.1.dist-info/top_level.txt
inputter-0.0.1.dist-info/RECORD
