Metadata-Version: 2.1
Name: inputter
Version: 0.0.1
Summary: Input detector
Home-page: https://repl.it/@mat1/inputter
Author: mat
Author-email: fake@email.lol
License: UNKNOWN
Platform: UNKNOWN
Classifier: Programming Language :: Python :: 3
Classifier: License :: OSI Approved :: MIT License
Classifier: Operating System :: OS Independent
